setup.py
mat_ev/__init__.py
mat_ev/matrix.py
mat_ev.egg-info/PKG-INFO
mat_ev.egg-info/SOURCES.txt
mat_ev.egg-info/dependency_links.txt
mat_ev.egg-info/not-zip-safe
mat_ev.egg-info/top_level.txt