Metadata-Version: 1.0
Name: mat-ev
Version: 0.1
Summary: Matrix operations
Home-page: UNKNOWN
Author: UNKNOWN
Author-email: UNKNOWN
License: UNKNOWN
Platform: UNKNOWN
